ytrader/__init__.py
ytrader/analysis.py
ytrader/book.py
ytrader/qdata.py
ytrader/strategy.py
ytrader/trader.py
ytrader/tradetime.py
ytrader-0.1.dist-info/LICENSE.txt
ytrader-0.1.dist-info/METADATA
ytrader-0.1.dist-info/WHEEL
ytrader-0.1.dist-info/top_level.txt
ytrader-0.1.dist-info/RECORD
